[{"filename":"."},{"filename":".."},{"filename":".Trash"},{"filename":".all-all.html"},{"filename":".sync"},{"filename":"170.html"},{"filename":"17001-at3.html"},{"filename":"17002-small-generator-business.html"},{"filename":"17003-new-SPD-pattent-creation.html"},{"filename":"17003-new-SPD.html"},{"filename":"17004-mozzos-network.html"},{"filename":"17004-setup-coddmpany.html"},{"filename":"17004-setup-company-business-creation.html"},{"filename":"17004-setup-company-business-models.html"},{"filename":"17004-setup-company-business-situation.html"},{"filename":"17004-setup-company-estatutos.html"},{"filename":"17004-setup-company-estatutos2.html"},{"filename":"17004-setup-company-prices.html"},{"filename":"17004-setup-company-products.html"},{"filename":"17004-setup-company-puesta-en-marcha.html"},{"filename":"17004-setup-company-segmentation.html"},{"filename":"17004-setup-company.html"},{"filename":"17006-energy-building-efficienty.html"},{"filename":"17007-web-grantop.html"},{"filename":"17008-office-network.html"},{"filename":"17009-ADC-system.html"},{"filename":"17010-ml-trade-investing.html"},{"filename":"17012-Customer-Market-Research-metals.html"},{"filename":"17012-Customer-Market-Research-transformadores.html"},{"filename":"17012-Customer-Market-Research.html"},{"filename":"17012-Grandtop Customer-Market-Research.html"},{"filename":"17013-developer-learning.html"},{"filename":"17014-hipotecas.html"},{"filename":"17014-mozzos-network.html"},{"filename":"17016-test-network.html"},{"filename":"17020-coderbunker-sales.html"},{"filename":"17021-security-business.html"},{"filename":"17022-icubed4.html"},{"filename":"17023-learn-to-learn.html"},{"filename":"17025-tornado-contratar-servicios.html"},{"filename":"17029-recovering-learning.html"},{"filename":"17031-mining-etherum.html"},{"filename":"180.html"},{"filename":"18034-12-IEC-61400-12-1-2017.pdf"},{"filename":"18034-2-IEC-61400-2-2006.html"},{"filename":"18034-3-IEC-61400-3-2009.html"},{"filename":"18034-chinanmei.com.html"},{"filename":"18034-iec-AMD1-2010.html"},{"filename":"18034-iec-AMD1:2010.html"},{"filename":"18034-iec.html"},{"filename":"18034-lighning.html"},{"filename":"18034-qingdao-wind-energy-test.html"},{"filename":"18034-test.html"},{"filename":"18034-test2.html"},{"filename":"18034-thesis.html"},{"filename":"_finance-statistics-tools-institutions.html"},{"filename":"aaaa.html"},{"filename":"ai-.html"},{"filename":"ai-neunetworks.html"},{"filename":"ai-practical-machine-learning.html"},{"filename":"build-identity.html"},{"filename":"chinese-.html"},{"filename":"chinese-A1-review.html"},{"filename":"chinese-learn-A3.html"},{"filename":"chinese-learn.html"},{"filename":"chinese-listening.html"},{"filename":"chinese-listening2.html"},{"filename":"cibersecurity.html"},{"filename":"com-.html"},{"filename":"com-Foggs-Behavior-Model.html"},{"filename":"com-analysis-del-discurso-conversacional.html"},{"filename":"com-behaviour-nudge.html"},{"filename":"com-com-me-han-pugut-convencer.html"},{"filename":"com-communication-techniques-framework"},{"filename":"com-comunicacion-discurso-tiempos-TIC.html"},{"filename":"com-ejercicios-procedimientos-nlp.html"},{"filename":"com-facs-paul-ekman-emotion-revealed.html"},{"filename":"com-ideas-persuasion.html"},{"filename":"com-influence-cialdini.html"},{"filename":"com-influenceTTS.html"},{"filename":"com-mentes-flexibles.html"},{"filename":"com-nlp.html"},{"filename":"com-other"},{"filename":"com-persuasion-in-china.html"},{"filename":"com-persuasion-technology.html"},{"filename":"com-persuasion.html"},{"filename":"com-power"},{"filename":"com-read-techniques.html"},{"filename":"com-seduction.html"},{"filename":"com-semiotic"},{"filename":"com-the-advertising-mind.html"},{"filename":"coursera.html"},{"filename":"eco-.html"},{"filename":"eco-accounting.html"},{"filename":"eco-analysis-tools.html"},{"filename":"eco-china.html"},{"filename":"eco-commodities.html"},{"filename":"eco-economy-financials.html"},{"filename":"eco-economy-people-markets-policy.html"},{"filename":"eco-eu-competition-law.html"},{"filename":"eco-finance-statistics-tools-institutions.html"},{"filename":"eco-international-trade.html"},{"filename":"eco-laws.html"},{"filename":"eco-source-info.html"},{"filename":"eco-suppliers.html"},{"filename":"eco-taxes.html"},{"filename":"eco-theories-ideas.html"},{"filename":"eco-tobuy.html"},{"filename":"eco-word-trade-report-summary.html"},{"filename":"events-.html"},{"filename":"git.html"},{"filename":"grandtop-.html"},{"filename":"grandtop-at.html"},{"filename":"grandtop-automation-building.html"},{"filename":"grandtop-computer_network.html"},{"filename":"grandtop-iot.html"},{"filename":"grandtop-leads.html"},{"filename":"id-.html"},{"filename":"id-esreal-larealidad.html"},{"filename":"id-id"},{"filename":"ideas-.html"},{"filename":"ideas-art-concept.html"},{"filename":"ideas-art-concept3.html"},{"filename":"ideas-awake.html"},{"filename":"ideas-dones"},{"filename":"ideas-ideas.html"},{"filename":"ideas-selfcontrol.html"},{"filename":"ideas-state-of-art.html"},{"filename":"ideas-straw-dogs.html"},{"filename":"ideas-toreview12.html"},{"filename":"ideas-triggers.html"},{"filename":"it-.html"},{"filename":"it-DAPP.html"},{"filename":"it-agile.html"},{"filename":"it-angular-phone-cat.html"},{"filename":"it-angular.html"},{"filename":"it-cibersecurity.html"},{"filename":"it-computational-investing.html"},{"filename":"it-cryptocurrency-l1.html"},{"filename":"it-cryptocurrency-l2.html"},{"filename":"it-cryptocurrency-l3.html"},{"filename":"it-cryptocurrency-l4.html"},{"filename":"it-cryptocurrency.html"},{"filename":"it-embeded-operating-system.html"},{"filename":"it-frameworks.html"},{"filename":"it-image-audio-video-tools.html"},{"filename":"it-iot-software-architecture.html"},{"filename":"it-js-notation.html"},{"filename":"it-julia.html"},{"filename":"it-jupyter.html"},{"filename":"it-linux-course1-19.html"},{"filename":"it-linux-course19-.html"},{"filename":"it-linux-course5v3.html"},{"filename":"it-linux-extra.html"},{"filename":"it-linux.html"},{"filename":"it-lxd.html"},{"filename":"it-m1-DOM.html"},{"filename":"it-m1-ansible-introduction.html"},{"filename":"it-m1-ansible.html"},{"filename":"it-m1-css.html"},{"filename":"it-m1-editor-brain-ckeditorv3.html"},{"filename":"it-m1-html2.html"},{"filename":"it-m1-httacces-apache.html"},{"filename":"it-m1-javascript.html"},{"filename":"it-m1-jquery.html"},{"filename":"it-m1-js.html"},{"filename":"it-m1-jsmore.html"},{"filename":"it-m1-linux-search.html"},{"filename":"it-m1-linux.databases-mysql.html"},{"filename":"it-m1-linux.databases-postgres.html"},{"filename":"it-m1-linux.databases.html"},{"filename":"it-m1-lxc.html"},{"filename":"it-m1-networking.html"},{"filename":"it-marketing-automation.html"},{"filename":"it-meteor.html"},{"filename":"it-mongo.html"},{"filename":"it-network.html"},{"filename":"it-nodejs.html"},{"filename":"it-policies.html"},{"filename":"it-python.html"},{"filename":"it-scrapping.html"},{"filename":"it-sec.html"},{"filename":"it-seo-m32-reports-q4.html"},{"filename":"it-seo-sem.html"},{"filename":"it-server-side-development.html"},{"filename":"it-smart-brain.html"},{"filename":"it-software-design.html"},{"filename":"it-software.html"},{"filename":"it-steps-ml-trade-investing.html"},{"filename":"it-storage.html"},{"filename":"it-sublime.html"},{"filename":"it-trademl.html"},{"filename":"it-usable-security.html"},{"filename":"it-vi"},{"filename":"it-vi.html"},{"filename":"it-web-image-audio-video-tools.html"},{"filename":"learn-.html"},{"filename":"learn-learn.html"},{"filename":"learn-methods.html"},{"filename":"m1-.html"},{"filename":"m1-model-thinking-strategically.html"},{"filename":"m1-software.html"},{"filename":"m1-template.html"},{"filename":"me-.html"},{"filename":"me-body-food.html"},{"filename":"me-music.html"},{"filename":"me-travels-changjiakou.html"},{"filename":"me-travels.html"},{"filename":"mind-.html"},{"filename":"mind-buddhism-psycology.html"},{"filename":"mind-buddishm"},{"filename":"mind-inner.html"},{"filename":"mind-lucid-dreams.html"},{"filename":"mind-meditation.html"},{"filename":"music.html"},{"filename":"pritty-pictures.html"},{"filename":"pritty-translate.html"},{"filename":"prittytodo.html"},{"filename":"seo-coursera.html"},{"filename":"stt-00.html"},{"filename":"stt-02-10\u592a\u6781\u62f3\u548c\u745c\u4f3d.mp3.1.mp3.html"},{"filename":"stt-02-10\u592a\u6781\u62f3\u548c\u745c\u4f3d.mp3.2.mp3.html"},{"filename":"stt-05-13\u838e\u838e\u821e\u8e48\u5de5\u4f5c\u574a.mp3.1.mp3.html"},{"filename":"stt-1-1-1.mp3.html"},{"filename":"stt-1-1-2.mp3.html"},{"filename":"stt-1-1-3.mp3.html"},{"filename":"stt-1-1-4.mp3.html"},{"filename":"stt-1-1-5.mp3.html"},{"filename":"stt-1-2-1.mp3.html"},{"filename":"stt-1-2-2.mp3.html"},{"filename":"stt-1-2-3.mp3.html"},{"filename":"stt-1-2-4.mp3.html"},{"filename":"stt-1-3-1.mp3.html"},{"filename":"stt-1-3-2.mp3.html"},{"filename":"stt-1-3-3.mp3.html"},{"filename":"stt-1-3-4.mp3.html"},{"filename":"stt-1-3-5.mp3.html"},{"filename":"stt-1-4-1.mp3.html"},{"filename":"stt-1-4-2.mp3.html"},{"filename":"stt-1-4-3.mp3.html"},{"filename":"stt-1-4-4.mp3.html"},{"filename":"stt-1-5-1.mp3.html"},{"filename":"stt-1-5-2.mp3.html"},{"filename":"stt-1-5-3.mp3.html"},{"filename":"stt-1-5-4.mp3.html"},{"filename":"stt-1-6-1.mp3.html"},{"filename":"stt-1-6-2.mp3.html"},{"filename":"stt-1-6-3.mp3.html"},{"filename":"stt-1-6-4.mp3.html"},{"filename":"stt-11-3-2.mp3.html"},{"filename":"stt-11-4.mp3.html"},{"filename":"stt-17-4.mp3.html"},{"filename":"stt-2-1-1.mp3.html"},{"filename":"stt-2-1-2.mp3.html"},{"filename":"stt-2-1-3.mp3.html"},{"filename":"stt-2-1-4.mp3.html"},{"filename":"stt-2-2-1.mp3.html"},{"filename":"stt-2-2-2.mp3.html"},{"filename":"stt-2-2-3.mp3.html"},{"filename":"stt-2-3-1.mp3.html"},{"filename":"stt-2-3-2.mp3.html"},{"filename":"stt-2-3-3.mp3.html"},{"filename":"stt-2-3-4.mp3.html"},{"filename":"stt-2-3-5.mp3.html"},{"filename":"stt-2-4-1.mp3.html"},{"filename":"stt-2-4-2.mp3.html"},{"filename":"stt-2-4-3.mp3.html"},{"filename":"stt-2-4-4.mp3.html"},{"filename":"stt-2-4-5.mp3.html"},{"filename":"stt-2-5-1.mp3.html"},{"filename":"stt-2-5-2.mp3.html"},{"filename":"stt-2-5-3.mp3.html"},{"filename":"stt-2-5-4.mp3.html"},{"filename":"stt-2-5-5.mp3.html"},{"filename":"stt-2-5.mp3.html"},{"filename":"stt-2-6-1.mp3.html"},{"filename":"stt-2-6-2.mp3.html"},{"filename":"stt-2-6-3.mp3.html"},{"filename":"stt-3-1-1.mp3.html"},{"filename":"stt-3-1-2.mp3.html"},{"filename":"stt-3-1-3.mp3.html"},{"filename":"stt-3-1-4.mp3.html"},{"filename":"stt-3-2-1.mp3.html"},{"filename":"stt-3-2-2.mp3.html"},{"filename":"stt-3-2-3.mp3.html"},{"filename":"stt-3-2-4.mp3.html"},{"filename":"stt-3-2-5.mp3.html"},{"filename":"stt-3-3-1.mp3.html"},{"filename":"stt-3-3-2.mp3.html"},{"filename":"stt-3-3-3.mp3.html"},{"filename":"stt-3-3-4.mp3.html"},{"filename":"stt-3-3-5.mp3.html"},{"filename":"stt-3-3-6.mp3.html"},{"filename":"stt-3-4-1.mp3.html"},{"filename":"stt-3-4-2.mp3.html"},{"filename":"stt-3-4-3.mp3.html"},{"filename":"stt-3-4-4.mp3.html"},{"filename":"stt-3-5-1.mp3.html"},{"filename":"stt-3-5-2.mp3.html"},{"filename":"stt-3-5-3.mp3.html"},{"filename":"stt-3-5-4.mp3.html"},{"filename":"stt-3-5-5.mp3.html"},{"filename":"stt-3-6-1.mp3.html"},{"filename":"stt-3-6-2.mp3.html"},{"filename":"stt-3-6-3.mp3.html"},{"filename":"stt-4-1-1.mp3.html"},{"filename":"stt-4-1-2.mp3.html"},{"filename":"stt-4-1-3.mp3.html"},{"filename":"stt-4-1-4.mp3.html"},{"filename":"stt-4-2-1.mp3.html"},{"filename":"stt-4-2-2.mp3.html"},{"filename":"stt-4-2-3.mp3.html"},{"filename":"stt-4-3-1.mp3.html"},{"filename":"stt-4-3-2.mp3.html"},{"filename":"stt-4-3-3.mp3.html"},{"filename":"stt-4-3-4.mp3.html"},{"filename":"stt-4-3-5.mp3.html"},{"filename":"stt-4-4-1.mp3.html"},{"filename":"stt-4-4-2.mp3.html"},{"filename":"stt-4-4-3.mp3.html"},{"filename":"stt-4-4-4.mp3.html"},{"filename":"stt-4-4-5.mp3.html"},{"filename":"stt-4-5-1.mp3.html"},{"filename":"stt-4-5-2.mp3.html"},{"filename":"stt-4-5-3.mp3.html"},{"filename":"stt-4-5-4.mp3.html"},{"filename":"stt-4-5-5.mp3.html"},{"filename":"stt-4-6-1.mp3.html"},{"filename":"stt-4-6-2.mp3.html"},{"filename":"stt-4-6-3.mp3.html"},{"filename":"stt-4-6-4.mp3.html"},{"filename":"stt-4-6-5.mp3.html"},{"filename":"stt-4.04.mp3.0.pcm.html"},{"filename":"stt-4.04.mp3.1.pcm.html"},{"filename":"stt-4.05.mp3.0.pcm.html"},{"filename":"stt-4.05.mp3.1.pcm.html"},{"filename":"stt-4.06.mp3.0.pcm.html"},{"filename":"stt-4.06.mp3.1.pcm.html"},{"filename":"stt-4.07.mp3.0.pcm.html"},{"filename":"stt-4.07.mp3.1.pcm.html"},{"filename":"stt-4.08.mp3.0.pcm.html"},{"filename":"stt-4.08.mp3.1.pcm.html"},{"filename":"stt-4.09.mp3.0.pcm.html"},{"filename":"stt-4.09.mp3.1.pcm.html"},{"filename":"stt-4.10.mp3.0.pcm.html"},{"filename":"stt-4.10.mp3.1.pcm.html"},{"filename":"stt-4.11.mp3.0.pcm.html"},{"filename":"stt-4.11.mp3.1.pcm.html"},{"filename":"stt-4.12.mp3.0.pcm.html"},{"filename":"stt-4.12.mp3.1.pcm.html"},{"filename":"stt-4.13.mp3.0.pcm.html"},{"filename":"stt-4.13.mp3.1.pcm.html"},{"filename":"stt-4.14.mp3.1.mp3.html"},{"filename":"stt-4.14.mp3.2.mp3.html"},{"filename":"stt-4k.01.mp3.0.pcm.html"},{"filename":"stt-4k.01.mp3.1.mp3.html"},{"filename":"stt-4k.01.mp3.1.pcm.html"},{"filename":"stt-4k.01.mp3.2.mp3.html"},{"filename":"stt-4k.02.mp3.0.pcm.html"},{"filename":"stt-4k.02.mp3.1.mp3.html"},{"filename":"stt-4k.02.mp3.1.pcm.html"},{"filename":"stt-4k.03.mp3.0.pcm.html"},{"filename":"stt-4k.03.mp3.1.mp3.html"},{"filename":"stt-4k.03.mp3.1.pcm.html"},{"filename":"stt-4k.04.mp3.0.pcm.html"},{"filename":"stt-4k.04.mp3.1.mp3.html"},{"filename":"stt-4k.04.mp3.1.pcm.html"},{"filename":"stt-4k.05.mp3.0.pcm.html"},{"filename":"stt-4k.05.mp3.1.mp3.html"},{"filename":"stt-4k.05.mp3.1.pcm.html"},{"filename":"stt-4k.06.mp3.0.pcm.html"},{"filename":"stt-4k.06.mp3.1.mp3.html"},{"filename":"stt-4k.06.mp3.1.pcm.html"},{"filename":"stt-4k.07.mp3.0.pcm.html"},{"filename":"stt-4k.07.mp3.1.pcm.html"},{"filename":"stt-4k.09.mp3.1.mp3.html"},{"filename":"stt-4k.09.mp3.2.mp3.html"},{"filename":"stt-4k.09.mp3.3.mp3.html"},{"filename":"stt-4k.09.mp3.4.mp3.html"},{"filename":"stt-4k.16.mp3.0.pcm.html"},{"filename":"stt-4k.16.mp3.1.pcm.html"},{"filename":"stt-5-1-1.mp3.html"},{"filename":"stt-5-1-2.mp3.html"},{"filename":"stt-5-1-3.mp3.html"},{"filename":"stt-5-1-4.mp3.html"},{"filename":"stt-5-1-5.mp3.html"},{"filename":"stt-5-2-1.mp3.html"},{"filename":"stt-5-2-2.mp3.html"},{"filename":"stt-5-2-3.mp3.html"},{"filename":"stt-5-2-4.mp3.html"},{"filename":"stt-5-2-5.mp3.html"},{"filename":"stt-5-3-1.mp3.html"},{"filename":"stt-5-3-2.mp3.html"},{"filename":"stt-5-3-3.mp3.html"},{"filename":"stt-5-3-4.mp3.html"},{"filename":"stt-5-4-1.mp3.html"},{"filename":"stt-5-4-2.mp3.html"},{"filename":"stt-5-4-3.mp3.html"},{"filename":"stt-5-4-4.mp3.html"},{"filename":"stt-5-4-5.mp3.html"},{"filename":"stt-5-4-6.mp3.html"},{"filename":"stt-5-5-1.mp3.html"},{"filename":"stt-5-5-2.mp3.html"},{"filename":"stt-5-5-3.mp3.html"},{"filename":"stt-5-5-4.mp3.html"},{"filename":"stt-5-5-5.mp3.html"},{"filename":"stt-5-6-1.mp3.html"},{"filename":"stt-5-6-2.mp3.html"},{"filename":"stt-5-6-3.mp3.html"},{"filename":"stt-5-6-4.mp3.html"},{"filename":"stt-5-6-5.mp3.html"},{"filename":"stt-6-1-1.mp3.html"},{"filename":"stt-6-1-2.mp3.html"},{"filename":"stt-6-1-3.mp3.html"},{"filename":"stt-6-1-4.mp3.html"},{"filename":"stt-6-1-5.mp3.html"},{"filename":"stt-6-2-1.mp3.html"},{"filename":"stt-6-2-2.mp3.html"},{"filename":"stt-6-2-3.mp3.html"},{"filename":"stt-6-2-4.mp3.html"},{"filename":"stt-6-2-5.mp3.html"},{"filename":"stt-6-3-1.mp3.html"},{"filename":"stt-6-3-2.mp3.html"},{"filename":"stt-6-3-3.mp3.html"},{"filename":"stt-6-3-4.mp3.html"},{"filename":"stt-6-3-5.mp3.html"},{"filename":"stt-6-4-1.mp3.html"},{"filename":"stt-6-4-2.mp3.html"},{"filename":"stt-6-4-3.mp3.html"},{"filename":"stt-6-4-4.mp3.html"},{"filename":"stt-6-4-5.mp3.html"},{"filename":"stt-6-5-1.mp3.html"},{"filename":"stt-6-5-2.mp3.html"},{"filename":"stt-6-5-3.mp3.html"},{"filename":"stt-6-5-4.mp3.html"},{"filename":"stt-6-6-1.mp3.html"},{"filename":"stt-6-6-2.mp3.html"},{"filename":"stt-6-6-3.mp3.html"},{"filename":"stt-6-6-4.mp3.html"},{"filename":"stt-60250131X_1.mp3.0.pcm.html"},{"filename":"stt-60250131X_1.mp3.1.pcm.html"},{"filename":"stt-60250131X_1.mp4.mp3.1.mp3.html"},{"filename":"stt-7-1-1.mp3.html"},{"filename":"stt-7-1-2.mp3.html"},{"filename":"stt-7-1-3.mp3.html"},{"filename":"stt-7-1-4.mp3.html"},{"filename":"stt-7-1-5.mp3.html"},{"filename":"stt-7-1-6.mp3.html"},{"filename":"stt-7-2-1.mp3.html"},{"filename":"stt-7-2-2.mp3.html"},{"filename":"stt-7-2-3.mp3.html"},{"filename":"stt-7-2-4.mp3.html"},{"filename":"stt-7-2-5.mp3.html"},{"filename":"stt-7-3-1.mp3.html"},{"filename":"stt-7-3-2.mp3.html"},{"filename":"stt-7-3-3.mp3.html"},{"filename":"stt-7-3-4.mp3.html"},{"filename":"stt-7-3-5.mp3.html"},{"filename":"stt-7-4-1.mp3.html"},{"filename":"stt-7-4-2.mp3.html"},{"filename":"stt-7-4-3.mp3.html"},{"filename":"stt-7-4-4.mp3.html"},{"filename":"stt-7-4-5.mp3.html"},{"filename":"stt-7-5-1.mp3.html"},{"filename":"stt-7-5-2.mp3.html"},{"filename":"stt-7-5-3.mp3.html"},{"filename":"stt-7-5-4.mp3.html"},{"filename":"stt-7-5-5.mp3.html"},{"filename":"stt-7-6-1.mp3.html"},{"filename":"stt-7-6-2.mp3.html"},{"filename":"stt-7-6-3.mp3.html"},{"filename":"stt-7-6-4.mp3.html"},{"filename":"stt-7-6-5.mp3.html"},{"filename":"stt-8-1-1.mp3.html"},{"filename":"stt-8-1-2.mp3.html"},{"filename":"stt-8-1-3.mp3.html"},{"filename":"stt-8-1-4.mp3.html"},{"filename":"stt-8-1-5.mp3.html"},{"filename":"stt-8-2-1.mp3.html"},{"filename":"stt-8-2-2.mp3.html"},{"filename":"stt-8-2-3.mp3.html"},{"filename":"stt-8-2-4.mp3.html"},{"filename":"stt-8-2-5.mp3.html"},{"filename":"stt-8-3-1.mp3.html"},{"filename":"stt-8-3-2.mp3.html"},{"filename":"stt-8-3-3.mp3.html"},{"filename":"stt-8-3-4.mp3.html"},{"filename":"stt-8-3-5.mp3.html"},{"filename":"stt-8-3-6.mp3.html"},{"filename":"stt-8-4-1.mp3.html"},{"filename":"stt-8-4-2.mp3.html"},{"filename":"stt-8-4-3.mp3.html"},{"filename":"stt-8-4-4.mp3.html"},{"filename":"stt-8-4-5.mp3.html"},{"filename":"stt-8-5-1.mp3.html"},{"filename":"stt-8-5-2.mp3.html"},{"filename":"stt-8-5-3.mp3.html"},{"filename":"stt-8-5-4.mp3.html"},{"filename":"stt-8-5-5.mp3.html"},{"filename":"stt-8-6-1.mp3.html"},{"filename":"stt-8-6-2.mp3.html"},{"filename":"stt-8-6-3.mp3.html"},{"filename":"stt-Call@01083051620(01083051620)_20170927165534.mp3.html"},{"filename":"stt-Call@01086391937(01086391937)_20170902122535.mp3.html"},{"filename":"stt-Call@10108888(10108888)_20171127135128.mp3.html"},{"filename":"stt-Call@15611140564(15611140564)_20171115103648.mp3.html"},{"filename":"stt-aaa.mp3.html"},{"filename":"stt-c-4.11..mp3.0.pcm.html"},{"filename":"stt-c-4.11..mp3.1.pcm.html"},{"filename":"stt-c-4k.07.mp3.html"},{"filename":"stt-c-4k.08.mp3.html"},{"filename":"stt-c-4k.09.mp3.html"},{"filename":"stt-c-4k.10.mp3.html"},{"filename":"stt-c-4k.11.mp3.html"},{"filename":"stt-c-4k.12.mp3.html"},{"filename":"stt-c-4k.13.mp3.html"},{"filename":"stt-c-4k.14.mp3.html"},{"filename":"stt-c-4k.15.mp3.html"},{"filename":"stt-c-4k.15.zfuxi.mp3.html"},{"filename":"stt-c-4k.16.mp3.html"},{"filename":"stt-c-4k.17.mp3.html"},{"filename":"stt-c-4k.18.mp3.html"},{"filename":"stt-c-4k.19.mp3.html"},{"filename":"stt-c-4k.20.mp3.html"},{"filename":"stt-c-4k.20.zfuxi.mp3.html"},{"filename":"stt-lighting.mp3.html"},{"filename":"stt-lightmono.mp3.html"},{"filename":"stt-pp.mp3.html"},{"filename":"stt-ppp.mp3.html"},{"filename":"stt-test.mp3.0.pcm.html"},{"filename":"stt-test.mp3.1.mp3.html"},{"filename":"stt-test.mp3.1.pcm.html"},{"filename":"stt-test.mp3.2.pcm.html"},{"filename":"stt-test.mp3.html"},{"filename":"stt-vlc-record-2017-11-23-16h46m44s-4k.09.mp3-.mp3.0.pcm.html"},{"filename":"stt-\u542c1.10-1.mp3.0.pcm.html"},{"filename":"stt-\u542c1.10-2.mp3.0.pcm.html"},{"filename":"stt-\u542c1.10-2.mp3.1.pcm.html"},{"filename":"stt-\u542c1.10-2.mp3.2.pcm.html"},{"filename":"stt-\u542c1.10-2.mp3.3.pcm.html"},{"filename":"stt-\u542c1.10-2.mp3.4.pcm.html"},{"filename":"stt-\u542c1.10-3-1.mp3.0.pcm.html"},{"filename":"stt-\u542c1.10-3-2.mp3.0.pcm.html"},{"filename":"stt-\u542c1.10-3.mp3.0.pcm.html"},{"filename":"stt-\u542c1.10-4.mp3.0.pcm.html"},{"filename":"stt-\u542c1.10-5.mp3.0.pcm.html"},{"filename":"stt-\u542c1.11-1.mp3.0.pcm.html"},{"filename":"stt-\u542c1.11-1.mp3.html"},{"filename":"stt-\u542c1.11-2.mp3.0.pcm.html"},{"filename":"stt-\u542c1.11-3-1.mp3.0.pcm.html"},{"filename":"stt-\u542c1.11-3-1.mp3.html"},{"filename":"stt-\u542c1.11-3-2.mp3.0.pcm.html"},{"filename":"stt-\u542c1.11-3-2.mp3.html"},{"filename":"stt-\u542c1.11-3.mp3.0.pcm.html"},{"filename":"stt-\u542c1.11-4.mp3.0.pcm.html"},{"filename":"stt-\u542c1.11-4.mp3.html"},{"filename":"stt-\u542c1.11-5.mp3.0.pcm.html"},{"filename":"stt-\u542c1.11-5.mp3.html"},{"filename":"stt-\u542c1.12-1.mp3.0.pcm.html"},{"filename":"stt-\u542c1.12-1.mp3.html"},{"filename":"stt-\u542c1.12-2.mp3.html"},{"filename":"stt-\u542c1.12-3.mp3.html"},{"filename":"stt-\u542c1.12-4.mp3.html"},{"filename":"stt-\u542c1.12-5.mp3.html"},{"filename":"stt-\u542c1.13-1.mp3.html"},{"filename":"stt-\u542c1.13-2.mp3.html"},{"filename":"stt-\u542c1.13-3-1.mp3.html"},{"filename":"stt-\u542c1.13-3-2.mp3.html"},{"filename":"stt-\u542c1.13-3.mp3.html"},{"filename":"stt-\u542c1.13-4.mp3.html"},{"filename":"stt-\u542c1.13-5.mp3.html"},{"filename":"stt-\u542c1.14-1.mp3.html"},{"filename":"stt-\u542c1.14-2.mp3.html"},{"filename":"stt-\u542c1.14-3-1.mp3.html"},{"filename":"stt-\u542c1.14-3-2.mp3.html"},{"filename":"stt-\u542c1.14-3.mp3.html"},{"filename":"stt-\u542c1.14-4.mp3.html"},{"filename":"stt-\u542c1.15-1.mp3.html"},{"filename":"stt-\u542c1.15-2.mp3.html"},{"filename":"stt-\u542c1.15-3.mp3.html"},{"filename":"stt-\u542c1.15-4.mp3.html"},{"filename":"stt-\u542c1.15-5.mp3.0.pcm.html"},{"filename":"stt-\u542c1.15-5.mp3.html"},{"filename":"stt-\u542c1.15-6.mp3.0.pcm.html"},{"filename":"stt-\u542c1.15-6.mp3.html"},{"filename":"stt-\u542c1.16-1.mp3.0.pcm.html"},{"filename":"stt-\u542c1.16-2.mp3.0.pcm.html"},{"filename":"stt-\u542c1.16-2.mp3.1.pcm.html"},{"filename":"stt-\u542c1.16-2.mp3.2.pcm.html"},{"filename":"stt-\u542c1.16-2.mp3.html"},{"filename":"stt-\u542c1.16-3-1.mp3.0.pcm.html"},{"filename":"stt-\u542c1.16-3-1.mp3.1.pcm.html"},{"filename":"stt-\u542c1.16-3-2.mp3.0.pcm.html"},{"filename":"stt-\u542c1.16-3-2.mp3.1.pcm.html"},{"filename":"stt-\u542c1.16-3.mp3.0.pcm.html"},{"filename":"stt-\u542c1.16-3.mp3.1.pcm.html"},{"filename":"stt-\u542c1.16-3.mp3.2.pcm.html"},{"filename":"stt-\u542c1.16-3.mp3.html"},{"filename":"stt-\u542c1.16-4.mp3.html"},{"filename":"stt-\u542c1.16-5.mp3.html"},{"filename":"stt-\u542c1.16-6.mp3.html"},{"filename":"stt-\u542c1.17-1.mp3.0.pcm.html"},{"filename":"stt-\u542c1.17-2.mp3.0.pcm.html"},{"filename":"stt-\u542c1.17-2.mp3.1.pcm.html"},{"filename":"stt-\u542c1.17-2.mp3.2.pcm.html"},{"filename":"stt-\u542c1.17-3-1.mp3.0.pcm.html"},{"filename":"stt-\u542c1.17-3-1.mp3.1.pcm.html"},{"filename":"stt-\u542c1.17-3-1.mp3.2.pcm.html"},{"filename":"stt-\u542c1.17-3-2.mp3.0.pcm.html"},{"filename":"stt-\u542c1.17-3-2.mp3.1.pcm.html"},{"filename":"stt-\u542c1.17-3-2.mp3.2.pcm.html"},{"filename":"stt-\u542c1.17-3.mp3.0.pcm.html"},{"filename":"stt-\u542c1.17-3.mp3.1.pcm.html"},{"filename":"stt-\u542c1.17-3.mp3.2.pcm.html"},{"filename":"stt-\u542c1.17-4.mp3.html"},{"filename":"stt-\u542c1.17-5.mp3.html"},{"filename":"stt-\u542c1.18-2.mp3.html"},{"filename":"stt-\u542c1.18-3-1.mp3.html"},{"filename":"stt-\u542c1.18-3-2.mp3.html"},{"filename":"stt-\u542c1.18-3.mp3.html"},{"filename":"stt-\u542c1.18-4.mp3.html"},{"filename":"stt-\u542c1.18-5.mp3.html"},{"filename":"stt-\u542c1.18-6.mp3.html"},{"filename":"stt-\u542c1.19-1.mp3.html"},{"filename":"stt-\u542c1.19-2.mp3.html"},{"filename":"stt-\u542c1.19-3-1.mp3.html"},{"filename":"stt-\u542c1.19-3-2.mp3.html"},{"filename":"stt-\u542c1.19-3.mp3.html"},{"filename":"stt-\u542c1.19-4.mp3.html"},{"filename":"stt-\u542c1.19-5.mp3.html"},{"filename":"stt-\u542c1.19-6.mp3.html"},{"filename":"stt-\u542c1.20-1.mp3.html"},{"filename":"stt-\u542c1.20-2.mp3.html"},{"filename":"stt-\u542c1.20-3-1.mp3.html"},{"filename":"stt-\u542c1.20-3-2.mp3.html"},{"filename":"stt-\u542c1.20-3-3.mp3.html"},{"filename":"stt-\u542c1.20-3.mp3.html"},{"filename":"stt-\u542c1.20-4.mp3.html"},{"filename":"stt-\u542c1.20-5.mp3.html"},{"filename":"stt-\u542c1.21-1.mp3.html"},{"filename":"stt-\u542c1.21-2.mp3.html"},{"filename":"stt-\u542c1.21-3.mp3.html"},{"filename":"stt-\u542c1.21-4.mp3.html"},{"filename":"stt-\u542c1.21-5.mp3.html"},{"filename":"stt-\u542c1.22-1.mp3.html"},{"filename":"stt-\u542c1.22-2.mp3.html"},{"filename":"stt-\u542c1.22-3.mp3.html"},{"filename":"stt-\u542c1.22-4.mp3.html"},{"filename":"stt-\u542c1.22-5.mp3.html"},{"filename":"stt-\u542c1.22-6.mp3.html"},{"filename":"stt-\u542c1.23-1.mp3.html"},{"filename":"stt-\u542c1.23-2.mp3.html"},{"filename":"stt-\u542c1.23-3-1.mp3.html"},{"filename":"stt-\u542c1.23-3-2.mp3.html"},{"filename":"stt-\u542c1.23-3.mp3.html"},{"filename":"stt-\u542c1.23-4.mp3.html"},{"filename":"stt-\u542c1.23-5.mp3.html"},{"filename":"stt-\u542c1.23-6.mp3.html"},{"filename":"stt-\u542c1.24-1.mp3.html"},{"filename":"stt-\u542c1.24-2.mp3.html"},{"filename":"stt-\u542c1.24-3.mp3.html"},{"filename":"stt-\u542c1.24-4.mp3.html"},{"filename":"stt-\u542c1.24-5.mp3.html"},{"filename":"stt-\u542c1.25-1.mp3.html"},{"filename":"stt-\u542c1.25-2.mp3.html"},{"filename":"stt-\u542c1.25-3.mp3.html"},{"filename":"stt-\u542c1.25-4.mp3.html"},{"filename":"stt-\u542c1.25-5.mp3.html"},{"filename":"stt-\u542c1.25-6.mp3.html"},{"filename":"stt-\u542c1.26-1.mp3.html"},{"filename":"stt-\u542c1.26-2.mp3.html"},{"filename":"stt-\u542c1.26-3.mp3.html"},{"filename":"stt-\u542c1.26-4.mp3.html"},{"filename":"stt-\u542c1.26-5.mp3.html"},{"filename":"stt-\u542c1.26-6.mp3.html"},{"filename":"stt-\u542c1.27-1.mp3.html"},{"filename":"stt-\u542c1.27-2.mp3.html"},{"filename":"stt-\u542c1.27-3.mp3.html"},{"filename":"stt-\u542c1.27-4.mp3.html"},{"filename":"stt-\u542c1.27-5.mp3.html"},{"filename":"stt-\u542c1.27-6.mp3.html"},{"filename":"stt-\u542c1.28-1.mp3.html"},{"filename":"stt-\u542c1.28-2.mp3.html"},{"filename":"stt-\u542c1.28-3-1.mp3.html"},{"filename":"stt-\u542c1.28-3-2.mp3.html"},{"filename":"stt-\u542c1.28-3.mp3.html"},{"filename":"stt-\u542c1.28-4.mp3.html"},{"filename":"stt-\u542c1.28-5.mp3.html"},{"filename":"stt-\u542c1.29-1.mp3.html"},{"filename":"stt-\u542c1.29-2.mp3.html"},{"filename":"stt-\u542c1.29-3-1.mp3.html"},{"filename":"stt-\u542c1.29-3-2.mp3.html"},{"filename":"stt-\u542c1.29-3.mp3.html"},{"filename":"stt-\u542c1.29-4.mp3.html"},{"filename":"stt-\u542c1.29-5.mp3.html"},{"filename":"stt-\u542c1.5-1.mp3.0.pcm.html"},{"filename":"stt-\u542c1.5-2.mp3.0.pcm.html"},{"filename":"stt-\u542c1.5-3.mp3.0.pcm.html"},{"filename":"stt-\u542c1.5-4.mp3.0.pcm.html"},{"filename":"stt-\u542c1.5-5.mp3.0.pcm.html"},{"filename":"stt-\u542c1.6-1.mp3.0.pcm.html"},{"filename":"stt-\u542c1.6-2.mp3.0.pcm.html"},{"filename":"stt-\u542c1.6-3.mp3.0.pcm.html"},{"filename":"stt-\u542c1.6-4.mp3.0.pcm.html"},{"filename":"stt-\u542c1.6-5.mp3.0.pcm.html"},{"filename":"stt-\u542c1.6-6.mp3.0.pcm.html"},{"filename":"stt-\u542c1.7-1.mp3.0.pcm.html"},{"filename":"stt-\u542c1.7-2.mp3.0.pcm.html"},{"filename":"stt-\u542c1.7-3.mp3.0.pcm.html"},{"filename":"stt-\u542c1.7-4.mp3.0.pcm.html"},{"filename":"stt-\u542c1.7-5.mp3.0.pcm.html"},{"filename":"stt-\u542c1.7-6.mp3.0.pcm.html"},{"filename":"stt-\u542c1.8-1.mp3.0.pcm.html"},{"filename":"stt-\u542c1.8-2.mp3.0.pcm.html"},{"filename":"stt-\u542c1.8-3.mp3.0.pcm.html"},{"filename":"stt-\u542c1.8-4.mp3.0.pcm.html"},{"filename":"stt-\u542c1.9-1.mp3.0.pcm.html"},{"filename":"stt-\u542c1.9-2.mp3.0.pcm.html"},{"filename":"stt-\u542c1.9-3-1.mp3.0.pcm.html"},{"filename":"stt-\u542c1.9-3-2.mp3.0.pcm.html"},{"filename":"stt-\u542c1.9-3.mp3.0.pcm.html"},{"filename":"stt-\u542c1.9-4.mp3.0.pcm.html"},{"filename":"stt-\u542c1.9-5.mp3.0.pcm.html"},{"filename":"stt-\u542c1.9-6.mp3.0.pcm.html"},{"filename":"stt-\u542c1.9-7.mp3.0.pcm.html"},{"filename":"stt-\u542c\u529b\u8bfe\u672c.html"},{"filename":"stt-\u62fe\u7ea7\u6c49\u8bed.html"},{"filename":"stt-\u7b2c5\u7ea7.mp3.html"},{"filename":"test.html"},{"filename":"test10.html"},{"filename":"test11.html"},{"filename":"test9.html"},{"filename":"todo-.html"},{"filename":"todo-buy"},{"filename":"todo-daily.html"},{"filename":"todo-grandtop.html"},{"filename":"todo-longterm.html"},{"filename":"todo-personal.html"},{"filename":"todo-plan2017.html"},{"filename":"todo-read.html"},{"filename":"todo-review-test.html"},{"filename":"todo-review-test2.html"},{"filename":"todo-review-test3.html"},{"filename":"todo-review-test5.html"},{"filename":"todo-review-todo"},{"filename":"todo-todo.html"},{"filename":"trash"}]